slipperpy/__about__.py
slipperpy/__init__.py
slipperpy/client.py
slipperpy/exceptions.py
slipperpy/models.py
slipperpy-0.1.0.dist-info/METADATA
slipperpy-0.1.0.dist-info/WHEEL
slipperpy-0.1.0.dist-info/licenses/LICENSE
slipperpy-0.1.0.dist-info/RECORD
